jenkins_kit/JenkinsUtils.py
jenkins_kit/__init__.py
jenkins_kit-0.1.6.dist-info/METADATA
jenkins_kit-0.1.6.dist-info/WHEEL
jenkins_kit-0.1.6.dist-info/top_level.txt
jenkins_kit-0.1.6.dist-info/RECORD
